pmuxy/__init__.py
pmuxy/config.py
pmuxy-0.1.3.data/scripts/pmuxy
pmuxy-0.1.3.dist-info/METADATA
pmuxy-0.1.3.dist-info/RECORD
pmuxy-0.1.3.dist-info/WHEEL
pmuxy-0.1.3.dist-info/top_level.txt
