Metadata-Version: 2.1
Name: pmuxy
Version: 0.1.3
Summary: A tmux windows manager
Home-page: https://github.com/SAReyes/pmuxy
License: UNKNOWN
Platform: UNKNOWN
Requires-Dist: click
Requires-Dist: libtmux
Requires-Dist: pyyaml
